[
  {
    "line": 2,
    "elements": [
      {
        "start_timestamp": "2025-03-12T06:46:43.073Z",
        "line": 12,
        "name": "Successful login",
        "description": "",
        "id": "login-action;successful-login;;2",
        "type": "scenario",
        "keyword": "Scenario Outline",
        "steps": [
          {
            "result": {
              "duration": 7730622100,
              "status": "passed"
            },
            "line": 6,
            "name": "User is on Home Page",
            "match": {
              "location": "stepDefinination.LoginStepDefination.user_is_on_Home_Page()"
            },
            "keyword": "Given "
          },
          {
            "result": {
              "status": "undefined"
            },
            "line": 7,
            "name": "User  enters valid credentials \"Admin\" as username \"admin1234\" as password",
            "match": {},
            "keyword": "When "
          },
          {
            "result": {
              "status": "skipped"
            },
            "line": 8,
            "name": "user in on dashboard page",
            "match": {
              "location": "stepDefinination.LoginStepDefination.user_in_on_dashboard_page()"
            },
            "keyword": "Then "
          }
        ]
      },
      {
        "start_timestamp": "2025-03-12T06:46:50.866Z",
        "line": 13,
        "name": "Successful login",
        "description": "",
        "id": "login-action;successful-login;;3",
        "type": "scenario",
        "keyword": "Scenario Outline",
        "steps": [
          {
            "result": {
              "duration": 11507938700,
              "status": "passed"
            },
            "line": 6,
            "name": "User is on Home Page",
            "match": {
              "location": "stepDefinination.LoginStepDefination.user_is_on_Home_Page()"
            },
            "keyword": "Given "
          },
          {
            "result": {
              "status": "undefined"
            },
            "line": 7,
            "name": "User  enters valid credentials \"Admin\" as username \"admin12\" as password",
            "match": {},
            "keyword": "When "
          },
          {
            "result": {
              "status": "skipped"
            },
            "line": 8,
            "name": "user in on dashboard page",
            "match": {
              "location": "stepDefinination.LoginStepDefination.user_in_on_dashboard_page()"
            },
            "keyword": "Then "
          }
        ]
      }
    ],
    "name": "Login Action",
    "description": "    Description: This feature will test a LogIn and LogOut functionality",
    "id": "login-action",
    "keyword": "Feature",
    "uri": "file:src/test/resources/features/login.feature",
    "tags": []
  }
]